missingdata/__init__.py
missingdata/_version.py
missingdata/base.py
missingdata/config.py
missingdata/impute.py
missingdata/utils.py
missingdata-0.1.3.dist-info/LICENSE
missingdata-0.1.3.dist-info/METADATA
missingdata-0.1.3.dist-info/WHEEL
missingdata-0.1.3.dist-info/top_level.txt
missingdata-0.1.3.dist-info/RECORD
