Metadata-Version: 2.1
Name: missingdata
Version: 0.1.3
Summary: missing data visualization and imputation
Home-page: https://github.com/raamana/missingdata
Author: Pradeep Reddy Raamana
Author-email: raamana@gmail.com
License: Apache Software License 2.0
Keywords: missingdata
Platform: UNKNOWN
Classifier: Development Status :: 2 - Pre-Alpha
Classifier: Intended Audience :: Developers
Classifier: License :: OSI Approved :: Apache Software License
Classifier: Natural Language :: English
Classifier: Programming Language :: Python :: 3
Classifier: Programming Language :: Python :: 3.4
Classifier: Programming Language :: Python :: 3.5
Classifier: Programming Language :: Python :: 3.6
Classifier: Programming Language :: Python :: 3.7
Requires-Dist: numpy
Requires-Dist: pandas
Requires-Dist: xlrd
Requires-Dist: matplotlib
